turta_sensoruhat/Turta_Accel.py
turta_sensoruhat/Turta_Digital.py
turta_sensoruhat/Turta_Env_280.py
turta_sensoruhat/Turta_IRRemote.py
turta_sensoruhat/Turta_UV_Light.py
turta_sensoruhat/__init__.py
turta_sensoruhat-1.0.0.dist-info/LICENCE
turta_sensoruhat-1.0.0.dist-info/METADATA
turta_sensoruhat-1.0.0.dist-info/WHEEL
turta_sensoruhat-1.0.0.dist-info/top_level.txt
turta_sensoruhat-1.0.0.dist-info/RECORD
